Fancy_term/Fancy_term.py
Fancy_term/__init__.py
Fancy_term-0.10.dist-info/LICENSE.txt
Fancy_term-0.10.dist-info/METADATA
Fancy_term-0.10.dist-info/WHEEL
Fancy_term-0.10.dist-info/top_level.txt
Fancy_term-0.10.dist-info/RECORD
