Metadata-Version: 2.1
Name: Fancy-term
Version: 0.10
Summary: Make your python app look cooler
Home-page: https://github.com/Plawn/Fancy_term
Author: Plawn
Author-email: plawn.yay@gmail.com
License: apache-2.0
Platform: UNKNOWN
